synod/__init__.py
synod/synod_dll.py
synod-1.1.dist-info/LICENSE
synod-1.1.dist-info/METADATA
synod-1.1.dist-info/WHEEL
synod-1.1.dist-info/top_level.txt
synod-1.1.dist-info/RECORD
