Metadata-Version: 2.1
Name: synod
Version: 1.1
Summary: Python dictionary with synonyms
Home-page: https://github.com/gnifajio/synod
Author: Gnifajio None
Author-email: gnifajio@gmail.com
License: UNKNOWN
Platform: UNKNOWN
Classifier: Programming Language :: Python :: 3.10
Classifier: License :: OSI Approved :: MIT License
Classifier: Operating System :: OS Independent
Requires-Python: >=3.7
License-File: LICENSE
